unionai_actor_executor/_lib.abi3.so
unionai_actor_executor/__init__.py
unionai_actor-0.1.11.data/scripts/unionai-actor-bridge
unionai_actor-0.1.11.dist-info/RECORD
unionai_actor-0.1.11.dist-info/entry_points.txt
unionai_actor-0.1.11.dist-info/WHEEL
unionai_actor-0.1.11.dist-info/APL.txt
unionai_actor-0.1.11.dist-info/BSL.txt
unionai_actor-0.1.11.dist-info/METADATA
unionai_actor-0.1.11.dist-info/top_level.txt
